analytic_schema/__init__.py
analytic_schema/analytic_schema.json
analytic_schema/loader.py
analytic_schema/output.py
analytic_schema/parser.py
analytic_schema/validator.py
analytic_schema-1.0.7.dist-info/licenses/LICENSE.md
analytic_schema-1.0.7.dist-info/METADATA
analytic_schema-1.0.7.dist-info/WHEEL
analytic_schema-1.0.7.dist-info/top_level.txt
analytic_schema-1.0.7.dist-info/RECORD
