Metadata-Version: 2.4
Name: analytic-schema
Version: 1.0.7
Summary: I/O schema loader + validator for analytics notebooks
Author-email: Zachary Szewczyk <zacjszewczyk@gmail.com>
License: License
Project-URL: Homepage, https://github.com/zacjszewczyk/analytic-schema
Project-URL: Issues, https://github.com/zacjszewczyk/analytic-schemaissues
Classifier: Programming Language :: Python :: 3
Classifier: Operating System :: OS Independent
Requires-Python: >=3.8
License-File: LICENSE.md
Requires-Dist: pandas>=1.0
Dynamic: license-file
